LICENSE
MANIFEST.in
README.rst
setup.py
migrations/__init__.py
weboffice365.egg-info/PKG-INFO
weboffice365.egg-info/SOURCES.txt
weboffice365.egg-info/dependency_links.txt
weboffice365.egg-info/top_level.txt